gspaces/__init__.py
gspaces/linear.py
gspaces/log.py
gspaces-0.3.0.dist-info/LICENSE
gspaces-0.3.0.dist-info/METADATA
gspaces-0.3.0.dist-info/WHEEL
gspaces-0.3.0.dist-info/top_level.txt
gspaces-0.3.0.dist-info/RECORD
