Metadata-Version: 2.1
Name: gspaces
Version: 0.3.0
Summary: Memory efficient alternative for range spaces.
Author: Quinten Star
License: MIT
Keywords: numpy,arange,range,linspace,geomspace,logspace,generators
Platform: UNKNOWN
Classifier: Programming Language :: Python :: 3
Classifier: Programming Language :: Python :: 3.7
Classifier: License :: OSI Approved :: MIT License
Classifier: Operating System :: OS Independent
Requires-Python: >=3.7
License-File: LICENSE
